jupyter_shared_drive/__init__.py
jupyter_shared_drive-0.2.1.dist-info/METADATA
jupyter_shared_drive-0.2.1.dist-info/WHEEL
jupyter_shared_drive-0.2.1.dist-info/licenses/LICENSE
jupyter_shared_drive-0.2.1.dist-info/RECORD
